HackKit/__init__.py
HackKit/core.py
hackkit-1.0.0.dist-info/licenses/LICENSE
hackkit-1.0.0.dist-info/METADATA
hackkit-1.0.0.dist-info/WHEEL
hackkit-1.0.0.dist-info/top_level.txt
hackkit-1.0.0.dist-info/RECORD
